coinshot/__init__.py
coinshot/coinshot.py
coinshot-3.2.2.data/scripts/shoot
coinshot-3.2.2.dist-info/LICENSE
coinshot-3.2.2.dist-info/METADATA
coinshot-3.2.2.dist-info/WHEEL
coinshot-3.2.2.dist-info/top_level.txt
coinshot-3.2.2.dist-info/RECORD
