Metadata-Version: 2.1
Name: coinshot
Version: 3.2.2
Summary: simple python module for pushover.net
Home-page: https://github.com/charlesthomas/coinshot
Author: Charles Thomas
Author-email: ch@rlesthom.as
License: MIT License
Platform: UNKNOWN
Classifier: Development Status :: 5 - Production/Stable
Classifier: Intended Audience :: Developers
Classifier: Intended Audience :: End Users/Desktop
Classifier: License :: OSI Approved :: MIT License
Classifier: Operating System :: MacOS :: MacOS X
Classifier: Operating System :: POSIX :: Linux
Classifier: Programming Language :: Python :: 2.7
Classifier: Programming Language :: Python :: 3
Classifier: Topic :: Communications
Classifier: Topic :: Software Development :: Libraries :: Python Modules
Requires-Dist: simplejson (>=3.3.0)
